dokan/__about__.py
dokan/__init__.py
dokan/__main__.py
dokan/_types.py
dokan/config.json
dokan/config.py
dokan/entry.py
dokan/monitor.py
dokan/nnlojet.py
dokan/order.py
dokan/preproduction.py
dokan/runcard.py
dokan/scheduler.py
dokan/task.py
dokan/ui.py
dokan/util.py
dokan/bib/__init__.py
dokan/bib/_references.py
dokan/combine/__init__.py
dokan/combine/_algo.py
dokan/combine/_plot.py
dokan/combine/_util.py
dokan/db/__init__.py
dokan/db/_dbdispatch.py
dokan/db/_dbmerge.py
dokan/db/_dbresurrect.py
dokan/db/_dbrunner.py
dokan/db/_dbtask.py
dokan/db/_jobstatus.py
dokan/db/_loglevel.py
dokan/db/_sqla.py
dokan/exe/__init__.py
dokan/exe/_exe_config.py
dokan/exe/_exe_data.py
dokan/exe/_executor.py
dokan/exe/htcondor/__init__.py
dokan/exe/htcondor/htcondor.template
dokan/exe/htcondor/lxplus.template
dokan/exe/local/__init__.py
dokan/exe/slurm/__init__.py
dokan/exe/slurm/slurm.template
dokan-1.0.0.dist-info/METADATA
dokan-1.0.0.dist-info/WHEEL
dokan-1.0.0.dist-info/entry_points.txt
dokan-1.0.0.dist-info/licenses/LICENSE
dokan-1.0.0.dist-info/RECORD
