Metadata-Version: 2.4
Name: dokan
Version: 1.0.0
Summary: Automating the NNLOJET workflow
Project-URL: Homepage, https://nnlojet.hepforge.org
Project-URL: Documentation, https://github.com/aykhuss/dokan#readme
Project-URL: Issues, https://github.com/aykhuss/dokan/issues
Project-URL: Source, https://github.com/aykhuss/dokan
Author: NNLOJET
License-Expression: GPL-3.0-or-later
License-File: LICENSE
Requires-Python: >=3.10
Requires-Dist: luigi>=3.5.2
Requires-Dist: numpy>=2.1.3
Requires-Dist: rich>=13.9.4
Requires-Dist: sqlalchemy>=2.0.36
